deutschland/digitale_verwaltung/__init__.py
deutschland/digitale_verwaltung/api/__init__.py
deutschland/digitale_verwaltung/api/ars_api.py
deutschland/digitale_verwaltung/api/data_api.py
deutschland/digitale_verwaltung/api_client.py
deutschland/digitale_verwaltung/apis/__init__.py
deutschland/digitale_verwaltung/configuration.py
deutschland/digitale_verwaltung/exceptions.py
deutschland/digitale_verwaltung/model/__init__.py
deutschland/digitale_verwaltung/model/ars_dto.py
deutschland/digitale_verwaltung/model/dv_data_dto.py
deutschland/digitale_verwaltung/model/page_ars_dto.py
deutschland/digitale_verwaltung/model/page_dv_data_dto.py
deutschland/digitale_verwaltung/model/pageable_object.py
deutschland/digitale_verwaltung/model/sort_object.py
deutschland/digitale_verwaltung/model_utils.py
deutschland/digitale_verwaltung/models/__init__.py
deutschland/digitale_verwaltung/rest.py
de_digitale_verwaltung-1.0.0.dist-info/METADATA
de_digitale_verwaltung-1.0.0.dist-info/WHEEL
de_digitale_verwaltung-1.0.0.dist-info/RECORD
