Metadata-Version: 2.1
Name: de-digitale-verwaltung
Version: 1.0.0
Summary: API zum Digitalisierungsfortschritt der öffentlichen Verwaltung
Home-page: https://github.com/bundesAPI/digitale-verwaltung-api
License: Apache-2.0
Keywords: OpenAPI,OpenAPI-Generator,digitale-verwaltung,App,API
Author: BundesAPI
Author-email: kontakt@bund.dev
Requires-Python: >=3.6
Classifier: License :: OSI Approved :: Apache Software License
Classifier: Programming Language :: Python :: 3
Classifier: Programming Language :: Python :: 3.6
Classifier: Programming Language :: Python :: 3.7
Classifier: Programming Language :: Python :: 3.8
Classifier: Programming Language :: Python :: 3.9
Classifier: Programming Language :: Python :: 3.10
Classifier: Programming Language :: Python :: 3.11
Classifier: Programming Language :: Python :: 3.12
Requires-Dist: python-dateutil
Requires-Dist: urllib3 (>=1.25.3)
Project-URL: Bug Tracker, https://github.com/bundesAPI/digitale-verwaltung-api/issues
